smartsense/__init__.py
smartsense/smartsense.py
smartsense-1.0.dist-info/METADATA
smartsense-1.0.dist-info/WHEEL
smartsense-1.0.dist-info/top_level.txt
smartsense-1.0.dist-info/RECORD
